fds/__init__.py
fds/sdk/__init__.py
fds/sdk/FactSetPrivateMarkets/__init__.py
fds/sdk/FactSetPrivateMarkets/api_client.py
fds/sdk/FactSetPrivateMarkets/configuration.py
fds/sdk/FactSetPrivateMarkets/exceptions.py
fds/sdk/FactSetPrivateMarkets/model_utils.py
fds/sdk/FactSetPrivateMarkets/rest.py
fds/sdk/FactSetPrivateMarkets/api/__init__.py
fds/sdk/FactSetPrivateMarkets/api/data_items_api.py
fds/sdk/FactSetPrivateMarkets/api/financials_api.py
fds/sdk/FactSetPrivateMarkets/api/non_periodic_api.py
fds/sdk/FactSetPrivateMarkets/api/universe_api.py
fds/sdk/FactSetPrivateMarkets/apis/__init__.py
fds/sdk/FactSetPrivateMarkets/model/__init__.py
fds/sdk/FactSetPrivateMarkets/model/entity_match.py
fds/sdk/FactSetPrivateMarkets/model/entity_match_request.py
fds/sdk/FactSetPrivateMarkets/model/entity_match_request_input.py
fds/sdk/FactSetPrivateMarkets/model/entity_matches_response.py
fds/sdk/FactSetPrivateMarkets/model/error_response.py
fds/sdk/FactSetPrivateMarkets/model/error_response_sub_errors.py
fds/sdk/FactSetPrivateMarkets/model/field.py
fds/sdk/FactSetPrivateMarkets/model/fields_response.py
fds/sdk/FactSetPrivateMarkets/model/financials.py
fds/sdk/FactSetPrivateMarkets/model/financials_fields.py
fds/sdk/FactSetPrivateMarkets/model/financials_request.py
fds/sdk/FactSetPrivateMarkets/model/financials_response.py
fds/sdk/FactSetPrivateMarkets/model/non_periodic.py
fds/sdk/FactSetPrivateMarkets/model/non_periodic_fields.py
fds/sdk/FactSetPrivateMarkets/model/non_periodic_request.py
fds/sdk/FactSetPrivateMarkets/model/non_periodic_response.py
fds/sdk/FactSetPrivateMarkets/model/private_market_ids.py
fds/sdk/FactSetPrivateMarkets/models/__init__.py
fds.sdk.FactSetPrivateMarkets-1.0.14.dist-info/LICENSE
fds.sdk.FactSetPrivateMarkets-1.0.14.dist-info/METADATA
fds.sdk.FactSetPrivateMarkets-1.0.14.dist-info/WHEEL
fds.sdk.FactSetPrivateMarkets-1.0.14.dist-info/top_level.txt
fds.sdk.FactSetPrivateMarkets-1.0.14.dist-info/RECORD
